nav_dataverk/VERSION
nav_dataverk/__init__.py
nav_dataverk/api.py
nav_dataverk/dataverk.py
nav_dataverk/dataverk_context.py
nav_dataverk/elastic_search_updater.py
nav_dataverk/package_publisher.py
nav_dataverk/connectors/AWS_S3.py
nav_dataverk/connectors/__init__.py
nav_dataverk/connectors/azure_blob_storage.py
nav_dataverk/connectors/base.py
nav_dataverk/connectors/bucket_connector_factory.py
nav_dataverk/connectors/bucket_storage_base.py
nav_dataverk/connectors/elasticsearch.py
nav_dataverk/connectors/file_storage.py
nav_dataverk/connectors/google_storage.py
nav_dataverk/connectors/jsonstat.py
nav_dataverk/connectors/kafka.py
nav_dataverk/connectors/oracle.py
nav_dataverk/connectors/postgres.py
nav_dataverk/connectors/s3.py
nav_dataverk/connectors/sqldb.py
nav_dataverk/connectors/sqlite.py
nav_dataverk/connectors/ssb_api.py
nav_dataverk/connectors/storage.py
nav_dataverk/context/__init__.py
nav_dataverk/context/env_store.py
nav_dataverk/context/replacer.py
nav_dataverk/context/settings.py
nav_dataverk/context/settings_classes.py
nav_dataverk/context/values_importer.py
nav_dataverk/utils/__init__.py
nav_dataverk/utils/auth_mixin.py
nav_dataverk/utils/db_utils.py
nav_dataverk/utils/dp2elastic.py
nav_dataverk/utils/file_functions.py
nav_dataverk/utils/logger_mixin.py
nav_dataverk/utils/nbstripout.py
nav_dataverk/utils/notebook2script.py
nav_dataverk/utils/notebookname.py
nav_dataverk/utils/publish_data.py
nav_dataverk/utils/resource_discoverer.py
nav_dataverk/utils/ssb.py
nav_dataverk/utils/validators.py
nav_dataverk/utils/windows_safe_tempdir.py
nav_dataverk-0.0.1.dist-info/LICENSE.md
nav_dataverk-0.0.1.dist-info/METADATA
nav_dataverk-0.0.1.dist-info/WHEEL
nav_dataverk-0.0.1.dist-info/top_level.txt
nav_dataverk-0.0.1.dist-info/RECORD
