Metadata-Version: 2.1
Name: nav-dataverk
Version: 0.0.1
Summary: Serverless ETL framework
Home-page: https://github.com/navikt
Author: NAV IKT
Author-email: paul.bencze@nav.no
License: MIT
Project-URL: Bug Tracker, https://github.com/navikt
Project-URL: Documentation, https://github.com/navikt
Project-URL: Source Code, https://github.com/navikt
Keywords: datapackage serverless etl jupyter open-data
Platform: UNKNOWN
Classifier: Development Status :: 3 - Alpha
Classifier: License :: OSI Approved :: MIT License
Classifier: Programming Language :: Python :: 3.6
Classifier: Programming Language :: Python :: 3.7
Requires-Python: >=3.6
Requires-Dist: SQLAlchemy (==1.2.10)
Requires-Dist: boto3 (==1.9.11)
Requires-Dist: cx-Oracle (==7.1.0)
Requires-Dist: elasticsearch (==6.3.0)
Requires-Dist: fire (==0.1.3)
Requires-Dist: google-api-core (==1.8.0)
Requires-Dist: google-auth (==1.5.0)
Requires-Dist: google-cloud-core (==0.29.1)
Requires-Dist: google-cloud-storage (==1.14.0)
Requires-Dist: google-resumable-media (==0.3.2)
Requires-Dist: googleapis-common-protos (==1.5.8)
Requires-Dist: google-cloud-bigquery (==1.9.0)
Requires-Dist: hvac (==0.7.2)
Requires-Dist: importlib-resources (==1.0.2)
Requires-Dist: kafka-python (==1.4.4)
Requires-Dist: numpy (==1.15.2)
Requires-Dist: pandas (==0.23.3)
Requires-Dist: prometheus-client (==0.4.0)
Requires-Dist: protobuf (==3.7.0)
Requires-Dist: pyarrow (>=0.10.0)
Requires-Dist: pyjstat (==1.0.1)
Requires-Dist: requests (==2.21.0)
Requires-Dist: setuptools (==40.8.0)
Requires-Dist: Sphinx (==1.8.4)
Requires-Dist: typing (==3.6.6)
Requires-Dist: urllib3 (==1.24.1)
Requires-Dist: sphinx-rtd-theme (==0.4.2)
Requires-Dist: nbsphinx
Requires-Dist: avro-python3 (==1.8.2)
